autophonesync/adb.py
autophonesync/cli.py
autophonesync/udev_handler.py
autophonesync-0.3.0.dist-info/METADATA
autophonesync-0.3.0.dist-info/WHEEL
autophonesync-0.3.0.dist-info/entry_points.txt
autophonesync-0.3.0.dist-info/top_level.txt
autophonesync-0.3.0.dist-info/RECORD
